source/__init__.py
source/entities/__init__.py
source/frameworks_and_devices/__init__.py
source/frameworks_and_devices/cli.py
source/interface_adapters/__init__.py
source/interface_adapters/controller.py
source/use_cases/__init__.py
clean_architecture_cli-0.1.0.dist-info/LICENSE
clean_architecture_cli-0.1.0.dist-info/METADATA
clean_architecture_cli-0.1.0.dist-info/WHEEL
clean_architecture_cli-0.1.0.dist-info/entry_points.txt
clean_architecture_cli-0.1.0.dist-info/RECORD
