Metadata-Version: 2.1
Name: clean-architecture-cli
Version: 0.1.0
Summary: 
License: MIT
Author: Marco Carmona
Author-email: marcocarmonadev@outlook.com
Requires-Python: >=3.10,<4.0
Classifier: License :: OSI Approved :: MIT License
Classifier: Programming Language :: Python :: 3
Classifier: Programming Language :: Python :: 3.10
Classifier: Programming Language :: Python :: 3.11
Classifier: Programming Language :: Python :: 3.12
Requires-Dist: typer (>=0.12.3,<0.13.0)
